{
  "hash": "00dc01a3",
  "configHash": "b77dd7b0",
  "lockfileHash": "893e6021",
  "browserHash": "f54bbceb",
  "optimized": {
    "react": {
      "src": "../../node_modules/react/index.js",
      "file": "react.js",
      "fileHash": "6a10d2ad",
      "needsInterop": true
    },
    "react-dom/client": {
      "src": "../../node_modules/react-dom/client.js",
      "file": "react-dom_client.js",
      "fileHash": "270ab839",
      "needsInterop": true
    },
    "react-router-dom": {
      "src": "../../node_modules/react-router-dom/dist/index.mjs",
      "file": "react-router-dom.js",
      "fileHash": "76c3b94c",
      "needsInterop": false
    },
    "lucide-react": {
      "src": "../../node_modules/lucide-react/dist/esm/lucide-react.js",
      "file": "lucide-react.js",
      "fileHash": "edaa4c71",
      "needsInterop": false
    }
  },
  "chunks": {
    "chunk-L2Q2RVSC": {
      "file": "chunk-L2Q2RVSC.js"
    },
    "chunk-DDNM7ENY": {
      "file": "chunk-DDNM7ENY.js"
    }
  }
}
